xappt_qt/__init__.py
xappt_qt/__version__.py
xappt_qt/browser.py
xappt_qt/config.py
xappt_qt/constants.py
xappt_qt/launcher.py
xappt_qt/main.py
xappt_qt/gui/__init__.py
xappt_qt/gui/application.py
xappt_qt/gui/delegates/__init__.py
xappt_qt/gui/delegates/simple_item.py
xappt_qt/gui/delegates/tool_item.py
xappt_qt/gui/dialogs/__init__.py
xappt_qt/gui/dialogs/tool_ui_dialog.py
xappt_qt/gui/tab_pages/__init__.py
xappt_qt/gui/tab_pages/about.py
xappt_qt/gui/tab_pages/base.py
xappt_qt/gui/tab_pages/options.py
xappt_qt/gui/tab_pages/tools.py
xappt_qt/gui/ui/__init__.py
xappt_qt/gui/ui/browser.py
xappt_qt/gui/ui/browser_tab_about.py
xappt_qt/gui/ui/browser_tab_options.py
xappt_qt/gui/ui/browser_tab_tools.py
xappt_qt/gui/ui/console.py
xappt_qt/gui/ui/tool_interface.py
xappt_qt/gui/utilities/__init__.py
xappt_qt/gui/utilities/dark_palette.py
xappt_qt/gui/utilities/style.py
xappt_qt/gui/utilities/tray_icon.py
xappt_qt/gui/widgets/__init__.py
xappt_qt/gui/widgets/check_list.py
xappt_qt/gui/widgets/console.py
xappt_qt/gui/widgets/error_label.py
xappt_qt/gui/widgets/file_edit.py
xappt_qt/gui/widgets/table_edit.py
xappt_qt/gui/widgets/text_edit.py
xappt_qt/gui/widgets/tool_page/__init__.py
xappt_qt/gui/widgets/tool_page/widget.py
xappt_qt/gui/widgets/tool_page/converters/__init__.py
xappt_qt/gui/widgets/tool_page/converters/base.py
xappt_qt/gui/widgets/tool_page/converters/convert_bool.py
xappt_qt/gui/widgets/tool_page/converters/convert_float.py
xappt_qt/gui/widgets/tool_page/converters/convert_int.py
xappt_qt/gui/widgets/tool_page/converters/convert_list.py
xappt_qt/gui/widgets/tool_page/converters/convert_str.py
xappt_qt/plugins/__init__.py
xappt_qt/plugins/interfaces/__init__.py
xappt_qt/plugins/interfaces/headless.py
xappt_qt/plugins/interfaces/qt.py
xappt_qt/plugins/tools/__init__.py
xappt_qt/plugins/tools/examples/__init__.py
xappt_qt/plugins/tools/examples/auto_advance.py
xappt_qt/plugins/tools/examples/headless.py
xappt_qt/plugins/tools/examples/param_visibility.py
xappt_qt-0.9.10.dist-info/LICENSE
xappt_qt-0.9.10.dist-info/METADATA
xappt_qt-0.9.10.dist-info/WHEEL
xappt_qt-0.9.10.dist-info/entry_points.txt
xappt_qt-0.9.10.dist-info/top_level.txt
xappt_qt-0.9.10.dist-info/RECORD
