Metadata-Version: 2.1
Name: xappt-qt
Version: 0.9.10
Summary: Qt/PyQt5 interface plugin for xappt.
Home-page: https://github.com/cmontesano/xappt_qt
Author: Christopher Montesano
Author-email: cmdev.00+xappt@gmail.com
License: MIT
Platform: any
Classifier: Topic :: Utilities
Classifier: Development Status :: 4 - Beta
Classifier: Intended Audience :: Developers
Classifier: License :: OSI Approved :: MIT License
Classifier: Operating System :: OS Independent
Classifier: Programming Language :: Python :: 3
Classifier: Programming Language :: Python :: 3.7
Classifier: Programming Language :: Python :: 3.8
Classifier: Programming Language :: Python :: 3.9
Requires-Python: >=3.7, <4
License-File: LICENSE
Requires-Dist: Markdown (~=3.3.4)
Requires-Dist: pyperclip (~=1.8.2)
Requires-Dist: PyQt5 (~=5.15.4)
Requires-Dist: xappt (>=0.9.3)
